cfactory/__config__/__init__.py
cfactory/__config__/cfactory_config.py
cfactory/collections/__init__.py
cfactory/collections/illuminate_package.py
cfactory/collections/illuminate_project.py
cfactory/collections/project_config.py
cfactory/collections/unit_summary.py
cfactory/std_factories/__init__.py
cfactory/std_factories/bindings/__init__.py
cfactory/std_factories/bindings/pybind/__init__.py
cfactory/std_factories/bindings/pybind/check_pybind.py
cfactory/std_factories/bindings/pybind/enumerations.py
cfactory/std_factories/bindings/pybind/pybind_factory.py
cfactory/std_factories/bindings/pybind/pybind_opt.py
cfactory/std_factories/common_filters.py
cfactory/std_factories/cpp_file_formatter.py
cfactory/std_factories/factory.py
cfactory/std_factories/file_formatter.py
cfactory/std_factories/lambda.py
cfactory/std_factories/machine.py
cfactory/std_factories/mako_global.py
cfactory/std_factories/templates/cpp_file.mako
cfactory/std_factories/templates/file.mako
cfactory/std_factories/templates/lambda.mako
cfactory/std_factories/templates/py_file.mako
cfactory/std_factories/templates/pybind/pybind11.mako
cfactory/std_factories/templates/pybind/pybind11_includes.mako
cfactory/std_factories/templates/pybind/pybind11_module.mako
cfactory/std_factories/templates/pybind/pybind11_top.mako
cfactory/std_factories/templates/pybind/pybind_class.mako
cfactory/std_factories/templates/pybind/pybind_enum.mako
cfactory/std_factories/templates/pybind/pybind_fparam.mako
cfactory/std_factories/templates/pybind/pybind_function.mako
cfactory/std_factories/templates/pybind/pybind_member.mako
cfactory/std_factories/templates/pybind/pybind_member_function.mako
cfactory/std_factories/templates/pybind/pybind_trampoline.mako
cfactory/std_factories/templates/pybind/pybind_union.mako
cfactory/std_factories/templates/pybind/pybind_variable.mako
cfactory/std_factories/templates/util_defs.mako
cfactory/utils/file_sys.py
cfactory/utils/load_summary.py
cfactory-0.1.0.dist-info/LICENSE
cfactory-0.1.0.dist-info/WHEEL
cfactory-0.1.0.dist-info/METADATA
cfactory-0.1.0.dist-info/RECORD
